hyprpy/__init__.py
hyprpy/components/__init__.py
hyprpy/components/common.py
hyprpy/components/instances.py
hyprpy/components/instancesignals.py
hyprpy/components/monitors.py
hyprpy/components/windows.py
hyprpy/components/workspaces.py
hyprpy/data/__init__.py
hyprpy/data/models.py
hyprpy/data/validators.py
hyprpy/utils/__init__.py
hyprpy/utils/assertions.py
hyprpy/utils/shell.py
hyprpy/utils/signals.py
hyprpy/utils/sockets.py
hyprpy-0.2.1.dist-info/licenses/LICENSE
hyprpy-0.2.1.dist-info/METADATA
hyprpy-0.2.1.dist-info/WHEEL
hyprpy-0.2.1.dist-info/top_level.txt
hyprpy-0.2.1.dist-info/RECORD
