Metadata-Version: 2.4
Name: hyprpy
Version: 0.2.1
Summary: Python bindings for the Hyprland compositor.
Author: Julian Lobbes
Author-email: julian@lobbes.dev
Project-URL: repo, https://github.com/ulinja/hyprpy
Project-URL: docs, https://hyprpy.lobbes.dev/
Keywords: hyprland,wayland,compositor,window manager
Classifier: Development Status :: 2 - Pre-Alpha
Classifier: License :: OSI Approved :: MIT License
Classifier: Operating System :: POSIX :: Linux
Classifier: Topic :: Desktop Environment :: Window Managers
Classifier: Topic :: Software Development :: Libraries
Classifier: Topic :: Software Development :: Libraries :: Python Modules
Classifier: Typing :: Typed
Classifier: Programming Language :: Python
Classifier: Programming Language :: Python :: 3
Classifier: Programming Language :: Python :: 3 :: Only
Classifier: Programming Language :: Python :: 3.7
Classifier: Programming Language :: Python :: 3.8
Classifier: Programming Language :: Python :: 3.9
Classifier: Programming Language :: Python :: 3.10
Classifier: Programming Language :: Python :: 3.11
Classifier: Programming Language :: Python :: 3.12
Classifier: Programming Language :: Python :: 3.13
Classifier: Programming Language :: Python :: 3.14
Requires-Python: >=3.7
License-File: LICENSE
Requires-Dist: pydantic>=2.1.1
Dynamic: license-file
